jikime-cookai/__init__.py
jikime-cookai/langchain/__init__.py
jikime-cookai/langchain/cost.py
jikime-cookai/langchain/llm.py
jikime-cookai/utils/__init__.py
jikime-cookai/utils/str.py
jikime_cookai/__init__.py
jikime_cookai/langchain/__init__.py
jikime_cookai/langchain/cost.py
jikime_cookai/langchain/llm.py
jikime_cookai/utils/__init__.py
jikime_cookai/utils/str.py
langchain/__init__.py
langchain/cost.py
langchain/llm.py
utils/__init__.py
utils/str.py
jikime_cookai-0.1.6.dist-info/LICENSE
jikime_cookai-0.1.6.dist-info/METADATA
jikime_cookai-0.1.6.dist-info/WHEEL
jikime_cookai-0.1.6.dist-info/top_level.txt
jikime_cookai-0.1.6.dist-info/RECORD
