Metadata-Version: 2.1
Name: jikime_cookai
Version: 0.1.6
Summary: Jikime Cook AI
Home-page: https://github.com/jikime/jikime-cookai
Author: Anthony.Kim
Author-email: jikime@gmail.com
Classifier: Programming Language :: Python :: 3
Classifier: License :: OSI Approved :: MIT License
Classifier: Operating System :: OS Independent
Requires-Python: >=3.10
License-File: LICENSE
